dialogflow_log_parser/__init__.py
dialogflow_log_parser/es/__init__.py
dialogflow_log_parser/es/parser.py
dialogflow_log_parser/es/logic/__init__.py
dialogflow_log_parser/es/logic/conf_logic.py
dialogflow_log_parser/es/logic/dict_logic.py
dialogflow_log_parser/es/logic/hocon_logic.py
dialogflow_log_parser-0.0.4.dist-info/LICENSE
dialogflow_log_parser-0.0.4.dist-info/METADATA
dialogflow_log_parser-0.0.4.dist-info/WHEEL
dialogflow_log_parser-0.0.4.dist-info/top_level.txt
dialogflow_log_parser-0.0.4.dist-info/RECORD
