Metadata-Version: 2.1
Name: dialogflow-log-parser
Version: 0.0.4
Summary: parse dialogflow log string
Home-page: https://github.com/PeterYusuke/dialogflow-log-parser
Author: Peter Yusuke
Author-email: yyamashita1201@gmail.com
Keywords: dialogflow parse log hocon
Classifier: License :: OSI Approved :: Apache Software License
Classifier: Programming Language :: Python :: 3
License-File: LICENSE
Requires-Dist: pyhocon (==0.3.59)
